claim_extractor/__init__.py
claim_extractor/llm_extract.py
claim_extractor/schemas/.linked_trust.meta.swp
claim_extractor/schemas/__init__.py
claim_extractor/schemas/linked_trust.json
claim_extractor/schemas/linked_trust.meta
claim_extractor/schemas/loader.py
linked_claim_extractor-0.1.0.dist-info/METADATA
linked_claim_extractor-0.1.0.dist-info/WHEEL
linked_claim_extractor-0.1.0.dist-info/licenses/LICENSE
linked_claim_extractor-0.1.0.dist-info/RECORD
